camxes.py
setup.py
lojbantools.egg-info/PKG-INFO
lojbantools.egg-info/SOURCES.txt
lojbantools.egg-info/dependency_links.txt
lojbantools.egg-info/top_level.txt