Metadata-Version: 1.0
Name: lojbantools
Version: 0.2.2
Summary: This package offers access to a bunch of lojban tools.
Home-page: UNKNOWN
Author: Timo Paulssen
Author-email: timo+lojbantools@wakelift.de
License: BSD
Download-URL: http://wakelift.de/lojban/software/python/lojbantools-0.2.2.tar.gz
Platform: UNKNOWN
Classifier: Development Status :: 3 - Alpha
Classifier: Intended Audience :: Developers
Classifier: License :: OSI Approved :: BSD License
Classifier: Operating System :: OS Independent
Classifier: Programming Language :: Python
Classifier: Topic :: Text Processing :: Linguistic
